ucplotter/__init__.py
ucplotter/ucplotter.py
ucplotter-0.1.0.dist-info/LICENSE
ucplotter-0.1.0.dist-info/WHEEL
ucplotter-0.1.0.dist-info/METADATA
ucplotter-0.1.0.dist-info/RECORD
